bmi_era5/__init__.py
bmi_era5/_version.py
bmi_era5/bmi.py
bmi_era5/utils.py
bmi_era5-0.1.4.dist-info/LICENSE.txt
bmi_era5-0.1.4.dist-info/METADATA
bmi_era5-0.1.4.dist-info/WHEEL
bmi_era5-0.1.4.dist-info/top_level.txt
bmi_era5-0.1.4.dist-info/RECORD
