Metadata-Version: 2.1
Name: bmi-era5
Version: 0.1.4
Summary: BMI implementation for ERA5 data https://confluence.ecmwf.int/display/CKB/ERA5
Home-page: http://csdms.colorado.edu
Author: Tian Gan
Author-email: jamy127@foxmail.com
License-File: LICENSE.txt
Requires-Dist: bmipy
Requires-Dist: netcdf4
Requires-Dist: numpy
Requires-Dist: pyyaml
Requires-Dist: requests
Requires-Dist: xarray
